{
  "parent": "minecraft:recipes/root",
  "criteria": {
    "has_matter": {
      "conditions": {
        "items": [
          {
            "items": [
              "equivalentexchange:red_matter"
            ]
          }
        ]
      },
      "trigger": "minecraft:inventory_changed"
    },
    "has_the_recipe": {
      "conditions": {
        "recipe": "equivalentexchange:rm_legs"
      },
      "trigger": "minecraft:recipe_unlocked"
    }
  },
  "requirements": [
    [
      "has_the_recipe",
      "has_matter"
    ]
  ],
  "rewards": {
    "recipes": [
      "equivalentexchange:rm_legs"
    ]
  }
}